waveassist/__init__.py
waveassist/_config.py
waveassist/cli.py
waveassist/constants.py
waveassist/core.py
waveassist/utils.py
waveassist-0.4.1.dist-info/licenses/LICENSE
waveassist-0.4.1.dist-info/METADATA
waveassist-0.4.1.dist-info/WHEEL
waveassist-0.4.1.dist-info/entry_points.txt
waveassist-0.4.1.dist-info/top_level.txt
waveassist-0.4.1.dist-info/RECORD
