Metadata-Version: 2.4
Name: waveassist
Version: 0.4.1
Summary: WaveAssist Python SDK for storing and retrieving structured data, LLM integration, and credit management
Home-page: https://github.com/waveassist/waveassist
Author: WaveAssist
Author-email: kakshil.shah@waveassist.io
Classifier: Development Status :: 3 - Alpha
Classifier: Intended Audience :: Developers
Classifier: Topic :: Software Development :: Libraries
Classifier: License :: OSI Approved :: MIT License
Classifier: Programming Language :: Python :: 3
Classifier: Programming Language :: Python :: 3.10
Classifier: Programming Language :: Python :: 3.11
Classifier: Programming Language :: Python :: 3.12
Classifier: Operating System :: OS Independent
Requires-Python: >=3.10
License-File: LICENSE
Requires-Dist: pandas>=1.0.0
Requires-Dist: requests>=2.32.4
Requires-Dist: python-dotenv>=1.1.1
Requires-Dist: pydantic>=2.0.0
Requires-Dist: openai>=2.11.0
Dynamic: author
Dynamic: author-email
Dynamic: classifier
Dynamic: description
Dynamic: description-content-type
Dynamic: home-page
Dynamic: license-file
Dynamic: requires-dist
Dynamic: requires-python
Dynamic: summary
